{
    "root": "ܥܐ",
    "id": 13342,
    "verb_class": "Geminate",
    "conjugations": {
        "881": {
            "value": "ܥܰܐ",
            "alternatives": []
        },
        "922": {
            "value": "ܥܰܐܶܐ",
            "alternatives": []
        },
        "967": {
            "value": "ܐܶܬܥܰܐܰܐ",
            "alternatives": []
        },
        "1003": {
            "value": "ܐܰܥܶܐ",
            "alternatives": []
        },
        "1047": {
            "value": "ܐܶܬܬܰܥܰܐ",
            "alternatives": []
        },
        "880": {
            "value": "ܥܶܐܰܬ",
            "alternatives": []
        },
        "921": {
            "value": "ܥܰܐܐܰܬ",
            "alternatives": []
        },
        "966": {
            "value": "ܐܶܬܥܰܐܐܰܬ",
            "alternatives": []
        },
        "1002": {
            "value": "ܐܰܥܐܰܬ",
            "alternatives": []
        },
        "1046": {
            "value": "ܐܶܬܬܰܥܐܰܬ",
            "alternatives": []
        },
        "879": {
            "value": "ܥܰܐܬ",
            "alternatives": []
        },
        "920": {
            "value": "ܥܰܐܶܐܬ",
            "alternatives": []
        },
        "965": {
            "value": "ܐܶܬܥܰܐܰܐܬ",
            "alternatives": []
        },
        "1001": {
            "value": "ܐܰܥܶܐܬ",
            "alternatives": []
        },
        "1045": {
            "value": "ܐܶܬܬܰܥܰܐܬ",
            "alternatives": []
        },
        "878": {
            "value": "ܥܰܐܬܝ",
            "alternatives": []
        },
        "919": {
            "value": "ܥܰܐܶܐܬܝ",
            "alternatives": []
        },
        "964": {
            "value": "ܐܶܬܥܰܐܰܐܬܝ",
            "alternatives": []
        },
        "1000": {
            "value": "ܐܰܥܶܐܬܝ",
            "alternatives": []
        },
        "1044": {
            "value": "ܐܶܬܬܰܥܐܬܝ",
            "alternatives": []
        },
        "877": {
            "value": "ܥܶܐܶܬ",
            "alternatives": []
        },
        "918": {
            "value": "ܥܰܐܐܶܬ",
            "alternatives": []
        },
        "963": {
            "value": "ܐܶܬܥܰܐܐܶܬ",
            "alternatives": []
        },
        "999": {
            "value": "ܐܰܥܐܶܬ",
            "alternatives": []
        },
        "1043": {
            "value": "ܐܶܬܬܰܥܐܶܬ",
            "alternatives": []
        },
        "875": {
            "value": "ܥܰܐܘ",
            "alternatives": [
                "ܥܰܐܽܘܢ"
            ]
        },
        "916": {
            "value": "ܥܰܐܶܐܘ",
            "alternatives": [
                "ܥܰܐܶܐܽܘܢ"
            ]
        },
        "961": {
            "value": "ܐܶܬܥܰܐܰܐܘ",
            "alternatives": [
                "ܐܶܬܥܰܐܰܐܽܘܢ"
            ]
        },
        "997": {
            "value": "ܐܰܥܶܐܘ",
            "alternatives": [
                "ܐܰܥܶܐܽܘܢ"
            ]
        },
        "1041": {
            "value": "ܐܶܬܬܰܥܰܐܘ",
            "alternatives": [
                "ܐܶܬܬܰܥܰܐܽܘܢ"
            ]
        },
        "873": {
            "value": "ܥܰܐ̈ܝ",
            "alternatives": [
                "ܥܰܐ̈ܶܝܢ"
            ]
        },
        "914": {
            "value": "ܥܰܐܶܐ̈ܝ",
            "alternatives": [
                "ܥܰܐܶܐ̈ܶܝܢ"
            ]
        },
        "959": {
            "value": "ܐܶܬܥܰܐܰܐ̈ܝ",
            "alternatives": [
                "ܐܶܬܥܰܐܰܐ̈ܶܝܢ"
            ]
        },
        "995": {
            "value": "ܐܰܥܶܐ̈ܝ",
            "alternatives": [
                "ܐܰܥܶܐ̈ܶܝܢ"
            ]
        },
        "1039": {
            "value": "ܐܶܬܬܰܥܰܐ̈ܝ",
            "alternatives": [
                "ܐܶܬܬܰܥܰܐ̈ܶܝܢ"
            ]
        },
        "872": {
            "value": "ܥܰܐܬܽܘܢ",
            "alternatives": []
        },
        "913": {
            "value": "ܥܰܐܶܐܬܽܘܢ",
            "alternatives": []
        },
        "958": {
            "value": "ܐܶܬܥܰܐܰܐܬܽܘܢ",
            "alternatives": []
        },
        "994": {
            "value": "ܐܰܥܶܐܬܽܘܢ",
            "alternatives": []
        },
        "1038": {
            "value": "ܐܶܬܬܰܥܰܐܬܽܘܢ",
            "alternatives": []
        },
        "871": {
            "value": "ܥܰܐܬ̈ܶܝܢ",
            "alternatives": []
        },
        "912": {
            "value": "ܥܰܐܶܐܬ̈ܶܝܢ",
            "alternatives": []
        },
        "957": {
            "value": "ܐܶܬܥܰܐܰܐ̈ܬܶܝܢ",
            "alternatives": []
        },
        "993": {
            "value": "ܐܰܥܶܐܬ̈ܶܝܢ",
            "alternatives": []
        },
        "1037": {
            "value": "ܐܶܬܬܰܥܰܐ̈ܬܶܝܢ",
            "alternatives": []
        },
        "869": {
            "value": "ܥܰܐܢ",
            "alternatives": [
                "ܥܰܐܢܰܢ"
            ]
        },
        "910": {
            "value": "ܥܰܐܶܐܢ",
            "alternatives": [
                "ܥܰܐܶܐܢܰܢ"
            ]
        },
        "955": {
            "value": "ܐܶܬܥܰܐܰܐܢ",
            "alternatives": [
                "ܐܶܬܥܰܐܰܐܢܰܢ"
            ]
        },
        "991": {
            "value": "ܐܰܥܶܐܢ",
            "alternatives": [
                "ܐܰܥܶܐܢܰܢ"
            ]
        },
        "1035": {
            "value": "ܐܶܬܬܰܥܰܐܢ",
            "alternatives": [
                "ܐܶܬܬܰܥܰܐܢܰܢ"
            ]
        },
        "860": {
            "value": "ܢܶܥܽܘܐ",
            "alternatives": []
        },
        "902": {
            "value": "ܢܥܰܐܶܐ",
            "alternatives": []
        },
        "941": {
            "value": "ܢܶܬܥܰܐܰܐ",
            "alternatives": []
        },
        "982": {
            "value": "ܢܰܥܶܐ",
            "alternatives": []
        },
        "1026": {
            "value": "ܢܶܬܬܰܥܰܐ",
            "alternatives": []
        },
        "858": {
            "value": "ܬܶܥܽܘܐ",
            "alternatives": [
                "ܬܶܥܽܘܐܝ"
            ]
        },
        "900": {
            "value": "ܬܥܰܐܶܐ",
            "alternatives": [
                "ܬܥܰܐܶܐܝ"
            ]
        },
        "939": {
            "value": "ܬܶܬܥܰܐܰܐ",
            "alternatives": [
                "ܬܶܬܥܰܐܰܐܝ"
            ]
        },
        "980": {
            "value": "ܬܰܥܶܐ",
            "alternatives": [
                "ܬܰܥܶܐܝ"
            ]
        },
        "1024": {
            "value": "ܬܶܬܬܰܥܰܐܝ",
            "alternatives": [
                "ܬܶܬܰܥܰܐܝ"
            ]
        },
        "857": {
            "value": "ܬܶܥܽܘܐ",
            "alternatives": []
        },
        "899": {
            "value": "ܬܥܰܐܶܐ",
            "alternatives": []
        },
        "938": {
            "value": "ܬܶܬܥܰܐܰܐ",
            "alternatives": []
        },
        "979": {
            "value": "ܬܰܥܶܐ",
            "alternatives": []
        },
        "1022": {
            "value": "ܬܶܬܬܰܥܰܐ",
            "alternatives": [
                "ܬܶܬܰܥܰܐ"
            ]
        },
        "856": {
            "value": "ܬܶܥܐܺܝܢ",
            "alternatives": []
        },
        "898": {
            "value": "ܬܥܰܐܐܺܝܢ",
            "alternatives": []
        },
        "937": {
            "value": "ܬܶܬܥܰܐܐܺܝܢ",
            "alternatives": []
        },
        "978": {
            "value": "ܬܰܥܐܺܝܢ",
            "alternatives": []
        },
        "1020": {
            "value": "ܬܶܬܬܰܥܰܐܺܝܢ",
            "alternatives": [
                "ܬܶܬܰܥܰܐܺܝܢ"
            ]
        },
        "855": {
            "value": "ܐܶܥܽܘܐ",
            "alternatives": []
        },
        "897": {
            "value": "ܐܶܥܰܐܶܐ",
            "alternatives": []
        },
        "936": {
            "value": "ܐܶܬܥܰܐܰܐ",
            "alternatives": []
        },
        "977": {
            "value": "ܐܰܥܶܐ",
            "alternatives": []
        },
        "1019": {
            "value": "ܐܶܬܬܰܥܰܐ",
            "alternatives": []
        },
        "854": {
            "value": "ܢܶܥܐܽܘܢ",
            "alternatives": []
        },
        "896": {
            "value": "ܢܥܰܐܐܽܘܢ",
            "alternatives": []
        },
        "935": {
            "value": "ܢܶܬܥܰܐܐܽܘܢ",
            "alternatives": []
        },
        "976": {
            "value": "ܢܰܥܐܽܘܢ",
            "alternatives": []
        },
        "1018": {
            "value": "ܢܶܬܬܰܥܐܽܘܢ",
            "alternatives": []
        },
        "853": {
            "value": "ܢܶܥ̈ܐܳܢ",
            "alternatives": []
        },
        "895": {
            "value": "ܢܥܰܐܐ̈ܳܢ",
            "alternatives": []
        },
        "934": {
            "value": "ܢܶܬܥܰܐܐ̈ܳܢ",
            "alternatives": []
        },
        "975": {
            "value": "ܢܰܥܐ̈ܳܢ",
            "alternatives": []
        },
        "1017": {
            "value": "ܢܶܬܬܰܥܐ̈ܳܢ",
            "alternatives": []
        },
        "852": {
            "value": "ܬܶܥܐܽܘܢ",
            "alternatives": []
        },
        "894": {
            "value": "ܬܥܰܐܐܽܘܢ",
            "alternatives": []
        },
        "933": {
            "value": "ܬܶܬܥܰܐܐܽܘܢ",
            "alternatives": []
        },
        "974": {
            "value": "ܬܰܥܐܽܘܢ",
            "alternatives": []
        },
        "1015": {
            "value": "ܬܶܬܬܰܥܐܽܘܢ",
            "alternatives": [
                "ܬܶܬܰܥܐܽܘܢ"
            ]
        },
        "851": {
            "value": "ܬܶܥ̈ܐܳܢ",
            "alternatives": []
        },
        "893": {
            "value": "ܬܥܰܐܐ̈ܳܢ",
            "alternatives": []
        },
        "932": {
            "value": "ܬܶܬܥܰܐܐ̈ܳܢ",
            "alternatives": []
        },
        "973": {
            "value": "ܬܰܥܐ̈ܳܢ",
            "alternatives": []
        },
        "1013": {
            "value": "ܬܶܬܬܰܥܐ̈ܳܢ",
            "alternatives": [
                "ܬܶܬܰܥܐ̈ܳܢ"
            ]
        },
        "850": {
            "value": "ܢܶܥܽܘܐ",
            "alternatives": []
        },
        "892": {
            "value": "ܢܥܰܐܶܐ",
            "alternatives": []
        },
        "931": {
            "value": "ܢܶܬܥܰܐܰܐ",
            "alternatives": []
        },
        "972": {
            "value": "ܢܰܥܶܐ",
            "alternatives": []
        },
        "1012": {
            "value": "ܢܶܬܬܰܥܰܐ",
            "alternatives": []
        },
        "868": {
            "value": "ܥܽܘܐ",
            "alternatives": []
        },
        "909": {
            "value": "ܥܰܐܶܐ",
            "alternatives": []
        },
        "953": {
            "value": "ܐܶܬܥܰܐܰܐ",
            "alternatives": [
                "ܐܶܬܥܰܐܐ"
            ]
        },
        "990": {
            "value": "ܐܰܥܶܐ",
            "alternatives": []
        },
        "1034": {
            "value": "ܐܶܬܬܰܥܰܐ",
            "alternatives": []
        },
        "866": {
            "value": "ܥܽܘܐܝ",
            "alternatives": [
                "ܥܽܘܐܺܝܢ"
            ]
        },
        "908": {
            "value": "ܥܰܐܶܐܝ",
            "alternatives": []
        },
        "951": {
            "value": "ܐܶܬܥܰܐܰܐܝ",
            "alternatives": [
                "ܐܶܬܥܰܐܐܝ"
            ]
        },
        "988": {
            "value": "ܐܰܥܶܐܝ",
            "alternatives": [
                "ܐܰܥܶܐܺܝܢ"
            ]
        },
        "1032": {
            "value": "ܐܶܬܬܰܥܰܐܝ",
            "alternatives": [
                "ܐܶܬܬܰܥܰܐܺܝܢ"
            ]
        },
        "864": {
            "value": "ܥܽܘܐܘ",
            "alternatives": [
                "ܥܽܘܐܽܘܢ"
            ]
        },
        "906": {
            "value": "ܥܰܐܶܐܘ",
            "alternatives": [
                "ܥܰܐܶܐܽܘܢ"
            ]
        },
        "947": {
            "value": "ܐܶܬܥܰܐܰܐܘ",
            "alternatives": [
                "ܐܶܬܥܰܐܐܽܘܢ",
                "ܐܶܬܥܰܐܰܐܽܘܢ",
                "ܐܶܬܥܰܐܐܘ"
            ]
        },
        "986": {
            "value": "ܐܰܥܶܐܘ",
            "alternatives": [
                "ܐܰܥܶܐܽܘܢ"
            ]
        },
        "1030": {
            "value": "ܐܶܬܬܰܥܰܐܘ",
            "alternatives": [
                "ܐܶܬܬܰܥܰܐܽܘܢ"
            ]
        },
        "862": {
            "value": "ܥܽܘܐ̈ܝ",
            "alternatives": [
                "ܥ̈ܽܘܐܶܝܢ"
            ]
        },
        "904": {
            "value": "ܥܰܐܶܐ̈ܝ",
            "alternatives": [
                "ܥܰܐܶܐ̈ܶܝܢ"
            ]
        },
        "943": {
            "value": "ܐܶܬܥܰܐܰܐ̈ܝ",
            "alternatives": [
                "ܐܶܬܥܰܐܐ̈ܶܝܢ",
                "ܐܶܬܥܰܐܰܐ̈ܶܝܢ",
                "ܐܶܬܥܰܐܐ̈ܝ"
            ]
        },
        "984": {
            "value": "ܐܰܥܶܐ̈ܝ",
            "alternatives": [
                "ܐܰܥܶܐ̈ܶܝܢ"
            ]
        },
        "1028": {
            "value": "ܐܶܬܬܰܥܰܐ̈ܝ",
            "alternatives": [
                "ܐܶܬܬܰܥܰܐ̈ܶܝܢ"
            ]
        },
        "849": {
            "value": "ܥܳܐܶܐ",
            "alternatives": []
        },
        "891": {
            "value": "ܡܥܰܐܶܐ",
            "alternatives": []
        },
        "930": {
            "value": "ܡܶܬܥܰܐܰܐ",
            "alternatives": []
        },
        "971": {
            "value": "ܡܰܥܶܐ",
            "alternatives": []
        },
        "1011": {
            "value": "ܡܶܬܬܰܥܰܐ",
            "alternatives": []
        },
        "848": {
            "value": "ܥܳܐܳܐ",
            "alternatives": []
        },
        "890": {
            "value": "ܡܥܰܐܐܳܐ",
            "alternatives": []
        },
        "929": {
            "value": "ܡܶܬܥܰܐܐܳܐ",
            "alternatives": []
        },
        "970": {
            "value": "ܡܰܥܐܳܐ",
            "alternatives": []
        },
        "1010": {
            "value": "ܡܶܬܬܰܥܐܳܐ",
            "alternatives": []
        },
        "847": {
            "value": "ܥܳܐܺܝܢ",
            "alternatives": []
        },
        "889": {
            "value": "ܡܥܰܐܐܺܝܢ",
            "alternatives": []
        },
        "928": {
            "value": "ܡܶܬܥܰܐܐܺܝܢ",
            "alternatives": []
        },
        "969": {
            "value": "ܡܰܥܐܺܝܢ",
            "alternatives": []
        },
        "1009": {
            "value": "ܡܶܬܬܰܥܰܐܺܝܢ",
            "alternatives": []
        },
        "846": {
            "value": "ܥܳܐ̈ܳܢ",
            "alternatives": []
        },
        "888": {
            "value": "ܡܥܰܐܐ̈ܳܢ",
            "alternatives": []
        },
        "927": {
            "value": "ܡܶܬܥܰܐܐ̈ܳܢ",
            "alternatives": []
        },
        "968": {
            "value": "ܡܰܥܐ̈ܳܢ",
            "alternatives": []
        },
        "1008": {
            "value": "ܡܶܬܬܰܥܰܐ̈ܳܢ",
            "alternatives": []
        },
        "886": {
            "value": "ܥܐܺܝܐ",
            "alternatives": []
        },
        "926": {
            "value": "ܡܥܰܐܰܐ",
            "alternatives": []
        },
        "1007": {
            "value": "ܡܰܥܰܐ",
            "alternatives": []
        },
        "884": {
            "value": "ܥܐܺܝܐܳܐ",
            "alternatives": []
        },
        "925": {
            "value": "ܡܥܰܐܐܳܐ",
            "alternatives": []
        },
        "1006": {
            "value": "ܡܰܥܐܳܐ",
            "alternatives": []
        },
        "883": {
            "value": "ܥܐܺܝܐܺܝܢ",
            "alternatives": []
        },
        "924": {
            "value": "ܡܥܰܐܐܺܝܢ",
            "alternatives": []
        },
        "1005": {
            "value": "ܡܰܥܐܺܝܢ",
            "alternatives": []
        },
        "882": {
            "value": "ܥܐܺܝܐ̈ܳܢ",
            "alternatives": []
        },
        "923": {
            "value": "ܡܥܰܐ̈ܐܳܢ",
            "alternatives": []
        },
        "1004": {
            "value": "ܡܰܥ̈ܐܳܢ",
            "alternatives": []
        },
        "861": {
            "value": "ܡܶܥܰܐ",
            "alternatives": []
        },
        "903": {
            "value": "ܡܥܰܐܳܐܽܘ",
            "alternatives": []
        },
        "942": {
            "value": "ܡܶܬܥܰܐܳܐܽܘ",
            "alternatives": []
        },
        "983": {
            "value": "ܡܰܥܳܐܽܘ",
            "alternatives": []
        },
        "1027": {
            "value": "ܡܶܬܬܰܥܳܐܽܘ",
            "alternatives": []
        }
    }
}